{"config":{"output_file":null,"full_docs":false,"pub_only":true,"reachable_only":true,"distro_crate":false,"signatures":false,"borrow_data":false},"version":"0.18.1","compilation":{"directory":[47,104,111,109,101,47,99,104,105,118,105,101,114,95,104,117,109,98,101,114,47,46,99,97,114,103,111,47,114,101,103,105,115,116,114,121,47,115,114,99,47,103,105,116,104,117,98,46,99,111,109,45,49,101,99,99,54,50,57,57,100,98,57,101,99,56,50,51,47,113,117,105,99,107,45,101,114,114,111,114,45,49,46,50,46,50],"program":"/home/chivier_humber/.rustup/toolchains/stable-x86_64-unknown-linux-gnu/bin/rls","arguments":["--crate-name","quick_error","/home/chivier_humber/.cargo/registry/src/github.com-1ecc6299db9ec823/quick-error-1.2.2/src/lib.rs","--color","never","--crate-type","lib","--emit=dep-info,link","-C","debuginfo=2","-C","metadata=7922e5169f66e962","-C","extra-filename=-7922e5169f66e962","--out-dir","/home/chivier_humber/Documents/rust_freertos/target/rls/debug/deps","-L","dependency=/home/chivier_humber/Documents/rust_freertos/target/rls/debug/deps","--cap-lints","allow","--error-format=json","--sysroot","/home/chivier_humber/.rustup/toolchains/stable-x86_64-unknown-linux-gnu"],"output":[47,104,111,109,101,47,99,104,105,118,105,101,114,95,104,117,109,98,101,114,47,68,111,99,117,109,101,110,116,115,47,114,117,115,116,95,102,114,101,101,114,116,111,115,47,116,97,114,103,101,116,47,114,108,115,47,100,101,98,117,103,47,100,101,112,115,47,108,105,98,113,117,105,99,107,95,101,114,114,111,114,45,55,57,50,50,101,53,49,54,57,102,54,54,101,57,54,50,46,114,108,105,98]},"prelude":{"crate_id":{"name":"quick_error","disambiguator":[12806774677878433630,2120292616374989176]},"crate_root":"/home/chivier_humber/.cargo/registry/src/github.com-1ecc6299db9ec823/quick-error-1.2.2/src","external_crates":[{"file_name":"/home/chivier_humber/.cargo/registry/src/github.com-1ecc6299db9ec823/quick-error-1.2.2/src/lib.rs","num":1,"id":{"name":"std","disambiguator":[853209657226342047,8462664850197014382]}},{"file_name":"/home/chivier_humber/.cargo/registry/src/github.com-1ecc6299db9ec823/quick-error-1.2.2/src/lib.rs","num":2,"id":{"name":"core","disambiguator":[772178867720458397,10513760593670507587]}},{"file_name":"/home/chivier_humber/.cargo/registry/src/github.com-1ecc6299db9ec823/quick-error-1.2.2/src/lib.rs","num":3,"id":{"name":"compiler_builtins","disambiguator":[17633954781163668134,3962627684191718065]}},{"file_name":"/home/chivier_humber/.cargo/registry/src/github.com-1ecc6299db9ec823/quick-error-1.2.2/src/lib.rs","num":4,"id":{"name":"rustc_std_workspace_core","disambiguator":[7858001605524721373,8369385247697161108]}},{"file_name":"/home/chivier_humber/.cargo/registry/src/github.com-1ecc6299db9ec823/quick-error-1.2.2/src/lib.rs","num":5,"id":{"name":"alloc","disambiguator":[5226771781757675641,11183407964508506038]}},{"file_name":"/home/chivier_humber/.cargo/registry/src/github.com-1ecc6299db9ec823/quick-error-1.2.2/src/lib.rs","num":6,"id":{"name":"libc","disambiguator":[15950205559580256541,6605390554280573401]}},{"file_name":"/home/chivier_humber/.cargo/registry/src/github.com-1ecc6299db9ec823/quick-error-1.2.2/src/lib.rs","num":7,"id":{"name":"rustc_demangle","disambiguator":[5066653915378193616,7813142097187859454]}},{"file_name":"/home/chivier_humber/.cargo/registry/src/github.com-1ecc6299db9ec823/quick-error-1.2.2/src/lib.rs","num":8,"id":{"name":"unwind","disambiguator":[1328488228804362593,9042026925657904388]}},{"file_name":"/home/chivier_humber/.cargo/registry/src/github.com-1ecc6299db9ec823/quick-error-1.2.2/src/lib.rs","num":9,"id":{"name":"backtrace_sys","disambiguator":[3005442698276396085,7194037300925619286]}},{"file_name":"/home/chivier_humber/.cargo/registry/src/github.com-1ecc6299db9ec823/quick-error-1.2.2/src/lib.rs","num":10,"id":{"name":"panic_unwind","disambiguator":[11662190156692096384,12505544175813687064]}}],"span":{"file_name":[47,104,111,109,101,47,99,104,105,118,105,101,114,95,104,117,109,98,101,114,47,46,99,97,114,103,111,47,114,101,103,105,115,116,114,121,47,115,114,99,47,103,105,116,104,117,98,46,99,111,109,45,49,101,99,99,54,50,57,57,100,98,57,101,99,56,50,51,47,113,117,105,99,107,45,101,114,114,111,114,45,49,46,50,46,50,47,115,114,99,47,108,105,98,46,114,115],"byte_start":0,"byte_end":45641,"line_start":1,"line_end":1309,"column_start":1,"column_end":2}},"imports":[],"defs":[{"kind":"Mod","id":{"krate":0,"index":0},"span":{"file_name":[47,104,111,109,101,47,99,104,105,118,105,101,114,95,104,117,109,98,101,114,47,46,99,97,114,103,111,47,114,101,103,105,115,116,114,121,47,115,114,99,47,103,105,116,104,117,98,46,99,111,109,45,49,101,99,99,54,50,57,57,100,98,57,101,99,56,50,51,47,113,117,105,99,107,45,101,114,114,111,114,45,49,46,50,46,50,47,115,114,99,47,108,105,98,46,114,115],"byte_start":0,"byte_end":45641,"line_start":1,"line_end":1309,"column_start":1,"column_end":2},"name":"","qualname":"::","value":"/home/chivier_humber/.cargo/registry/src/github.com-1ecc6299db9ec823/quick-error-1.2.2/src/lib.rs","parent":null,"children":[{"krate":0,"index":2},{"krate":0,"index":4},{"krate":0,"index":6},{"krate":0,"index":16},{"krate":0,"index":18},{"krate":0,"index":8},{"krate":0,"index":12}],"decl_id":null,"docs":" A macro which makes errors easy to write","sig":null,"attributes":[{"value":"warn(missing_docs)","span":{"file_name":[47,104,111,109,101,47,99,104,105,118,105,101,114,95,104,117,109,98,101,114,47,46,99,97,114,103,111,47,114,101,103,105,115,116,114,121,47,115,114,99,47,103,105,116,104,117,98,46,99,111,109,45,49,101,99,99,54,50,57,57,100,98,57,101,99,56,50,51,47,113,117,105,99,107,45,101,114,114,111,114,45,49,46,50,46,50,47,115,114,99,47,108,105,98,46,114,115],"byte_start":0,"byte_end":22,"line_start":1,"line_end":1,"column_start":1,"column_end":23}}]},{"kind":"Struct","id":{"krate":0,"index":16},"span":{"file_name":[47,104,111,109,101,47,99,104,105,118,105,101,114,95,104,117,109,98,101,114,47,46,99,97,114,103,111,47,114,101,103,105,115,116,114,121,47,115,114,99,47,103,105,116,104,117,98,46,99,111,109,45,49,101,99,99,54,50,57,57,100,98,57,101,99,56,50,51,47,113,117,105,99,107,45,101,114,114,111,114,45,49,46,50,46,50,47,115,114,99,47,108,105,98,46,114,115],"byte_start":34645,"byte_end":34652,"line_start":1005,"line_end":1005,"column_start":12,"column_end":19},"name":"Context","qualname":"::Context","value":"","parent":null,"children":[],"decl_id":null,"docs":" Generic context type","sig":null,"attributes":[]},{"kind":"Trait","id":{"krate":0,"index":8},"span":{"file_name":[47,104,111,109,101,47,99,104,105,118,105,101,114,95,104,117,109,98,101,114,47,46,99,97,114,103,111,47,114,101,103,105,115,116,114,121,47,115,114,99,47,103,105,116,104,117,98,46,99,111,109,45,49,101,99,99,54,50,57,57,100,98,57,101,99,56,50,51,47,113,117,105,99,107,45,101,114,114,111,114,45,49,46,50,46,50,47,115,114,99,47,108,105,98,46,114,115],"byte_start":34738,"byte_end":34747,"line_start":1008,"line_end":1008,"column_start":11,"column_end":20},"name":"ResultExt","qualname":"::ResultExt","value":"ResultExt<T, E>","parent":null,"children":[{"krate":0,"index":10}],"decl_id":null,"docs":" Result extension trait adding a `context` method\n","sig":null,"attributes":[]},{"kind":"Method","id":{"krate":0,"index":10},"span":{"file_name":[47,104,111,109,101,47,99,104,105,118,105,101,114,95,104,117,109,98,101,114,47,46,99,97,114,103,111,47,114,101,103,105,115,116,114,121,47,115,114,99,47,103,105,116,104,117,98,46,99,111,109,45,49,101,99,99,54,50,57,57,100,98,57,101,99,56,50,51,47,113,117,105,99,107,45,101,114,114,111,114,45,49,46,50,46,50,47,115,114,99,47,108,105,98,46,114,115],"byte_start":35091,"byte_end":35098,"line_start":1015,"line_end":1015,"column_start":8,"column_end":15},"name":"context","qualname":"::ResultExt::context","value":"fn <X> (self, x: X) -> Result<T, Context<X, E>>","parent":{"krate":0,"index":8},"children":[],"decl_id":null,"docs":" The method is use to add context information to current operation","sig":null,"attributes":[]}],"impls":[{"id":0,"kind":"Direct","span":{"file_name":[47,104,111,109,101,47,99,104,105,118,105,101,114,95,104,117,109,98,101,114,47,46,99,97,114,103,111,47,114,101,103,105,115,116,114,121,47,115,114,99,47,103,105,116,104,117,98,46,99,111,109,45,49,101,99,99,54,50,57,57,100,98,57,101,99,56,50,51,47,113,117,105,99,107,45,101,114,114,111,114,45,49,46,50,46,50,47,115,114,99,47,108,105,98,46,114,115],"byte_start":35177,"byte_end":35183,"line_start":1018,"line_end":1018,"column_start":32,"column_end":38},"value":"","parent":null,"children":[{"krate":0,"index":14}],"docs":"","sig":null,"attributes":[]}],"refs":[],"macro_refs":[],"relations":[{"span":{"file_name":[47,104,111,109,101,47,99,104,105,118,105,101,114,95,104,117,109,98,101,114,47,46,99,97,114,103,111,47,114,101,103,105,115,116,114,121,47,115,114,99,47,103,105,116,104,117,98,46,99,111,109,45,49,101,99,99,54,50,57,57,100,98,57,101,99,56,50,51,47,113,117,105,99,107,45,101,114,114,111,114,45,49,46,50,46,50,47,115,114,99,47,108,105,98,46,114,115],"byte_start":35177,"byte_end":35183,"line_start":1018,"line_end":1018,"column_start":32,"column_end":38},"kind":{"variant":"Impl","fields":[0]},"from":{"krate":2,"index":41420},"to":{"krate":0,"index":8}}]}